flodger/__init__.py
flodger/flodger.py
flodger-1.0.4.dist-info/METADATA
flodger-1.0.4.dist-info/WHEEL
flodger-1.0.4.dist-info/licenses/LICENSE
flodger-1.0.4.dist-info/RECORD
