Metadata-Version: 2.4
Name: flodger
Version: 1.0.4
Summary: A package for function-driven logging.
Author-email: Rob Wade <rwade@claimsconsortiumgroup.co.uk>
License-File: LICENSE
Classifier: License :: OSI Approved :: MIT License
Classifier: Operating System :: OS Independent
Classifier: Programming Language :: Python :: 3
Requires-Python: >=3.11
Requires-Dist: loguru
Requires-Dist: pandas
Requires-Dist: polars
